dash/__init__.py
dash/categories/__init__.py
dash/categories/fields.py
dash/categories/migrations/0001_initial.py
dash/categories/migrations/0002_auto_20140820_1415.py
dash/categories/migrations/0003_categoryimage.py
dash/categories/migrations/0004_auto_20140904_0927.py
dash/categories/migrations/0005_auto_20140922_1514.py
dash/categories/migrations/0006_auto_20141008_1955.py
dash/categories/migrations/0007_auto_20170301_0914.py
dash/categories/migrations/0008_alter_category_options.py
dash/categories/migrations/0009_auto_20210910_1450.py
dash/categories/migrations/0010_alter_category_created_by_alter_category_modified_by_and_more.py
dash/categories/migrations/0011_alter_category_unique_together_and_more.py
dash/categories/migrations/__init__.py
dash/categories/models.py
dash/categories/templates/categories/categoryimage_list.html
dash/categories/urls.py
dash/categories/views.py
dash/context_processors.py
dash/dashblocks/__init__.py
dash/dashblocks/migrations/0001_initial.py
dash/dashblocks/migrations/0002_auto_20140802_2112.py
dash/dashblocks/migrations/0003_auto_20140804_0236.py
dash/dashblocks/migrations/0004_auto_20140902_1200.py
dash/dashblocks/migrations/0005_auto_20140904_0957.py
dash/dashblocks/migrations/0006_auto_20140922_1514.py
dash/dashblocks/migrations/0007_auto_20170301_0914.py
dash/dashblocks/migrations/0008_auto_20210902_1125.py
dash/dashblocks/migrations/0009_auto_20210910_1450.py
dash/dashblocks/migrations/0010_alter_dashblock_created_by_and_more.py
dash/dashblocks/migrations/0011_alter_dashblock_index_together_and_more.py
dash/dashblocks/migrations/0012_rename_dashblock_org_is_active_dashblock_type_priority_dashblocks__org_id_024805_idx_and_more.py
dash/dashblocks/migrations/0013_rename_dashblocks__org_id_024805_idx_dashblock_org_typ_prio_idx_and_more.py
dash/dashblocks/migrations/__init__.py
dash/dashblocks/models.py
dash/dashblocks/static/css/font/summernote.eot
dash/dashblocks/static/css/font/summernote.ttf
rapidpro_dash-1.19.0.dist-info/LICENSE
rapidpro_dash-1.19.0.dist-info/METADATA
rapidpro_dash-1.19.0.dist-info/WHEEL
rapidpro_dash-1.19.0.dist-info/RECORD
