Metadata-Version: 2.3
Name: rapidpro-dash
Version: 1.19.0
Summary: Support library for RapidPro dashboards
License: BSD
Author: Nyaruka
Author-email: code@nyaruka.com
Requires-Python: >=3.11,<4.0
Classifier: Development Status :: 5 - Production/Stable
Classifier: Environment :: Web Environment
Classifier: Intended Audience :: Developers
Classifier: License :: OSI Approved :: BSD License
Classifier: Operating System :: OS Independent
Classifier: Programming Language :: Python
Classifier: Framework :: Django
Requires-Dist: Django (>=5.1.9,<5.3)
Requires-Dist: Pillow (>=9.4)
Requires-Dist: celery (>=5.1,<6.0)
Requires-Dist: django-compressor (>=4.0)
Requires-Dist: django-timezone-field (>=6.1.0)
Requires-Dist: django-valkey (>=0.2.1,<0.3.0)
Requires-Dist: isort[pyproject] (>=5.13.2)
Requires-Dist: phonenumbers (>=8.12.16)
Requires-Dist: psycopg (>=3.1.9)
Requires-Dist: python-dateutil (>=2.8.2)
Requires-Dist: rapidpro-python (>=2.18.0)
Requires-Dist: smartmin (>=5.2.2,<6.0.0)
Requires-Dist: sorl-thumbnail (>=12.9.0)
Project-URL: Repository, http://github.com/rapidpro/dash
